PoolFlow/__init__.py
PoolFlow/dynamic_pool.py
PoolFlow/lol.py
PoolFlow/server_pool.py
PoolFlow/static_pool.py
PoolFlow/tests/__init__.py
PoolFlow/tests/test_.py
PoolFlow/tests/test_pools.py
PoolFlow/utilities/__init__.py
PoolFlow/utilities/pool_utilities.py
PoolFlow-0.0.6.dist-info/METADATA
PoolFlow-0.0.6.dist-info/WHEEL
PoolFlow-0.0.6.dist-info/top_level.txt
PoolFlow-0.0.6.dist-info/RECORD
