Metadata-Version: 2.1
Name: PoolFlow
Version: 0.0.6
Summary: A simple process management library
Home-page: https://victorgarric.github.io/PoolFlow/
Author: Victor Garric
Author-email: victor.garric@gmail.com
License: MIT
Requires-Dist: rich
